grf_gp/__init__.py
grf_gp/inference.py
grf_gp/model.py
grf_gp/sampler.py
grf_gp/kernels/__init__.py
grf_gp/kernels/base.py
grf_gp/kernels/diffusion.py
grf_gp/kernels/general.py
grf_gp/utils/__init__.py
grf_gp/utils/config.py
grf_gp/utils/csr.py
grf_gp/utils/sampling.py
grf_gp/utils/sparse_lo.py
grf_gp/utils/spectral.py
grf_gp/utils/visual.py
fast_graph_gp-0.1.2.dist-info/METADATA
fast_graph_gp-0.1.2.dist-info/WHEEL
fast_graph_gp-0.1.2.dist-info/top_level.txt
fast_graph_gp-0.1.2.dist-info/RECORD
