Metadata-Version: 2.4
Name: fast-graph-gp
Version: 0.1.2
Summary: Graph Random Features for Scalable Gaussian Processes (GRF-GP)
Author-email: Matthew Zhang <matthew.zhang473@gmail.com>
License: MIT
Project-URL: Homepage, https://github.com/MatthewZhang473/GRF-GP
Project-URL: Repository, https://github.com/MatthewZhang473/GRF-GP
Project-URL: Documentation, https://github.com/MatthewZhang473/GRF-GP#readme
Project-URL: Issues, https://github.com/MatthewZhang473/GRF-GP/issues
Keywords: gaussian-processes,graph-kernels,machine-learning,pytorch
Classifier: Development Status :: 4 - Beta
Classifier: Intended Audience :: Science/Research
Classifier: License :: OSI Approved :: MIT License
Classifier: Operating System :: OS Independent
Classifier: Programming Language :: Python :: 3.10
Classifier: Programming Language :: Python :: 3.11
Classifier: Topic :: Scientific/Engineering :: Artificial Intelligence
Requires-Python: >=3.8
Requires-Dist: torch>=2.0.0
Requires-Dist: gpytorch>=1.10
Requires-Dist: numpy>=1.21.0
Requires-Dist: scipy>=1.10.0
Requires-Dist: tqdm>=4.65.0
